Metadata-Version: 2.1
Name: openswathidpicker
Version: 0.0.5
Summary: A protein inference package used for OpenSWATH data
Project-URL: Homepage, https://github.com/Roestlab/OpenSWATHIDPIcker
Project-URL: Bug Tracker, https://github.com/Roestlab/OpenSWATHIDPIcker/issues
Author-email: Kai Ren Chen <kairen.chen@mail.utoronto.com>
License: --------------------------------------------------------------------------
License-File: LICENSE
Classifier: Development Status :: 2 - Pre-Alpha
Classifier: Intended Audience :: Science/Research
Classifier: License :: OSI Approved :: BSD License
Classifier: Operating System :: OS Independent
Classifier: Programming Language :: Python :: 3
Classifier: Topic :: Scientific/Engineering :: Bio-Informatics
Requires-Python: >=3.7
